odoo/addons/partner_data_vies_populator/README.rst
odoo/addons/partner_data_vies_populator/__init__.py
odoo/addons/partner_data_vies_populator/__manifest__.py
odoo/addons/partner_data_vies_populator/i18n/fr.po
odoo/addons/partner_data_vies_populator/i18n/partner_data_vies_populator.pot
odoo/addons/partner_data_vies_populator/models/__init__.py
odoo/addons/partner_data_vies_populator/models/res_partner.py
odoo/addons/partner_data_vies_populator/readme/CONTRIBUTORS.rst
odoo/addons/partner_data_vies_populator/readme/DESCRIPTION.rst
odoo/addons/partner_data_vies_populator/readme/INSTALL.rst
odoo/addons/partner_data_vies_populator/readme/USAGE.rst
odoo/addons/partner_data_vies_populator/static/description/icon.png
odoo/addons/partner_data_vies_populator/static/description/index.html
odoo/addons/partner_data_vies_populator/tests/__init__.py
odoo/addons/partner_data_vies_populator/tests/test_partner_data_vies_populator.py
odoo14_addon_partner_data_vies_populator-14.0.1.0.3.dist-info/METADATA
odoo14_addon_partner_data_vies_populator-14.0.1.0.3.dist-info/WHEEL
odoo14_addon_partner_data_vies_populator-14.0.1.0.3.dist-info/top_level.txt
odoo14_addon_partner_data_vies_populator-14.0.1.0.3.dist-info/RECORD
