Metadata-Version: 2.1
Name: odoo14-addon-partner-data-vies-populator
Version: 14.0.1.0.3
Summary: Using VIES webservice, name and address information will be fetched and added to the partner.
Home-page: https://github.com/OCA/partner-contact
Author: NextERP Romania,Forest and Biomass Romania,Odoo Community Association (OCA)
Author-email: support@odoo-community.org
License: AGPL-3
Platform: UNKNOWN
Classifier: Programming Language :: Python
Classifier: Framework :: Odoo
Classifier: Framework :: Odoo :: 14.0
Classifier: License :: OSI Approved :: GNU Affero General Public License v3
Requires-Python: >=3.6
Requires-Dist: odoo (<14.1dev,>=14.0a)
Requires-Dist: python-stdnum
